pycg3d/__init__.py
pycg3d/cg3d_cords.py
pycg3d/cg3d_line.py
pycg3d/cg3d_plane.py
pycg3d/cg3d_point.py
pycg3d/cg3d_vector.py
pycg3d/utils.py
pycg3d/transform/__init__.py
pycg3d/transform/cg3d_reflect.py
pycg3d/transform/cg3d_rotate.py
pycg3d/transform/cg3d_transform.py
pycg3d/transform/cg3d_translate.py
pycg3d-0.0.1.dist-info/DESCRIPTION.rst
pycg3d-0.0.1.dist-info/METADATA
pycg3d-0.0.1.dist-info/RECORD
pycg3d-0.0.1.dist-info/WHEEL
pycg3d-0.0.1.dist-info/metadata.json
pycg3d-0.0.1.dist-info/top_level.txt
